Metadata-Version: 1.0
Name: alma-probablity
Version: 1.4
Summary: Gaussian and Binomial distributions
Home-page: UNKNOWN
Author: Ali Balati
Author-email: ali.balati@yahoo.com
License: UNKNOWN
Platform: UNKNOWN
